trailblazer/__init__.py
trailblazer/cli/__init__.py
trailblazer/cli/core.py
trailblazer/cli/utils/__init__.py
trailblazer/cli/utils/ls_helper.py
trailblazer/cli/utils/user_helper.py
trailblazer/clients/__init__.py
trailblazer/clients/authentication_client/__init__.py
trailblazer/clients/authentication_client/dtos/__init__.py
trailblazer/clients/authentication_client/dtos/refresh_token_request.py
trailblazer/clients/authentication_client/dtos/tokens_request.py
trailblazer/clients/authentication_client/dtos/tokens_response.py
trailblazer/clients/authentication_client/exceptions.py
trailblazer/clients/authentication_client/google_oauth_client.py
trailblazer/clients/google_api_client/__init__.py
trailblazer/clients/google_api_client/exceptions.py
trailblazer/clients/google_api_client/google_api_client.py
trailblazer/clients/slurm_api_client/__init__.py
trailblazer/clients/slurm_api_client/dto/__init__.py
trailblazer/clients/slurm_api_client/dto/cancel_job_response.py
trailblazer/clients/slurm_api_client/dto/common.py
trailblazer/clients/slurm_api_client/dto/job_response.py
trailblazer/clients/slurm_api_client/dto/jobs_response.py
trailblazer/clients/slurm_api_client/error_handler.py
trailblazer/clients/slurm_api_client/slurm_api_client.py
trailblazer/clients/slurm_cli_client/__init__.py
trailblazer/clients/slurm_cli_client/mapper.py
trailblazer/clients/slurm_cli_client/models.py
trailblazer/clients/slurm_cli_client/slurm_cli_client.py
trailblazer/clients/slurm_cli_client/utils.py
trailblazer/clients/tower/__init__.py
trailblazer/clients/tower/models.py
trailblazer/clients/tower/tower_client.py
trailblazer/clients/tower/utils.py
trailblazer/constants.py
trailblazer/containers.py
trailblazer/dto/__init__.py
trailblazer/dto/analyses_request.py
trailblazer/dto/analyses_response.py
trailblazer/dto/analysis_response.py
trailblazer/dto/analysis_update_request.py
trailblazer/dto/authentication/__init__.py
trailblazer/dto/authentication/code_exchange_request.py
trailblazer-21.10.7.dist-info/METADATA
trailblazer-21.10.7.dist-info/WHEEL
trailblazer-21.10.7.dist-info/entry_points.txt
trailblazer-21.10.7.dist-info/licenses/LICENSE
trailblazer-21.10.7.dist-info/RECORD
