Metadata-Version: 2.4
Name: trailblazer
Version: 21.10.7
Summary: Keep track of and manage analyses
License: MIT
License-File: LICENSE
Author: Your Name
Author-email: you@example.com
Requires-Python: >=3.12,<4.0
Classifier: License :: OSI Approved :: MIT License
Classifier: Programming Language :: Python :: 3
Classifier: Programming Language :: Python :: 3.12
Classifier: Programming Language :: Python :: 3.13
Classifier: Programming Language :: Python :: 3.14
Requires-Dist: Flask
Requires-Dist: Flask-Cors
Requires-Dist: MarkupSafe
Requires-Dist: PyMySQL
Requires-Dist: SQLAlchemy
Requires-Dist: alembic
Requires-Dist: click
Requires-Dist: coloredlogs
Requires-Dist: cryptography
Requires-Dist: dependency-injector
Requires-Dist: flask-reverse-proxy
Requires-Dist: google-auth
Requires-Dist: gunicorn
Requires-Dist: marshmallow
Requires-Dist: pydantic
Requires-Dist: requests
Requires-Dist: ruamel.yaml
Requires-Dist: setuptools
Requires-Dist: tabulate
